odoo10_addon_account_fiscal_year_closing-10.0.1.0.0-py2.7-nspkg.pth
odoo/addons/account_fiscal_year_closing/README.rst
odoo/addons/account_fiscal_year_closing/__init__.py
odoo/addons/account_fiscal_year_closing/__manifest__.py
odoo/addons/account_fiscal_year_closing/i18n/es.po
odoo/addons/account_fiscal_year_closing/models/__init__.py
odoo/addons/account_fiscal_year_closing/models/account_fiscalyear_closing.py
odoo/addons/account_fiscal_year_closing/models/account_fiscalyear_closing_abstract.py
odoo/addons/account_fiscal_year_closing/models/account_fiscalyear_closing_template.py
odoo/addons/account_fiscal_year_closing/models/account_move.py
odoo/addons/account_fiscal_year_closing/security/account_fiscalyear_closing_security.xml
odoo/addons/account_fiscal_year_closing/security/ir.model.access.csv
odoo/addons/account_fiscal_year_closing/static/description/icon.png
odoo/addons/account_fiscal_year_closing/static/description/icon.svg
odoo/addons/account_fiscal_year_closing/views/account_fiscalyear_closing_template_views.xml
odoo/addons/account_fiscal_year_closing/views/account_fiscalyear_closing_views.xml
odoo/addons/account_fiscal_year_closing/views/account_move_views.xml
odoo/addons/account_fiscal_year_closing/wizards/__init__.py
odoo/addons/account_fiscal_year_closing/wizards/account_fiscal_year_closing_unbalanced_move.py
odoo/addons/account_fiscal_year_closing/wizards/account_fiscal_year_closing_unbalanced_move_views.xml
odoo10_addon_account_fiscal_year_closing-10.0.1.0.0.dist-info/DESCRIPTION.rst
odoo10_addon_account_fiscal_year_closing-10.0.1.0.0.dist-info/METADATA
odoo10_addon_account_fiscal_year_closing-10.0.1.0.0.dist-info/RECORD
odoo10_addon_account_fiscal_year_closing-10.0.1.0.0.dist-info/WHEEL
odoo10_addon_account_fiscal_year_closing-10.0.1.0.0.dist-info/metadata.json
odoo10_addon_account_fiscal_year_closing-10.0.1.0.0.dist-info/namespace_packages.txt
odoo10_addon_account_fiscal_year_closing-10.0.1.0.0.dist-info/top_level.txt
