Metadata-Version: 2.0
Name: odoo10-addon-account-fiscal-year-closing
Version: 10.0.1.0.0
Summary: Generic fiscal year closing wizard
Home-page: https://www.tecnativa.org/
Author: Tecnativa, Odoo Community Association (OCA)
Author-email: support@odoo-community.org
License: AGPL-3
Platform: UNKNOWN
Classifier: Programming Language :: Python
Classifier: Framework :: Odoo
Classifier: License :: OSI Approved :: GNU Affero General Public License v3
Requires-Python: ~=2.7
Requires-Dist: odoo (<10.1dev,>=10.0)
Requires-Dist: odoo10-addon-account-reversal
